tools/app.py
tools/excel/excel_images_to_base64.py
tools/excel/excel_merger_by_field.py
tools/excel/merge_all_in_folder.py
tools/excel/pythonExcelSplitter.py
tools/excel/python_field_comparer.py
tools/locust/locustfile.py
tools/template/__init__.py
tools/template/template.py
dv_tools-0.1.2.dist-info/METADATA
dv_tools-0.1.2.dist-info/WHEEL
dv_tools-0.1.2.dist-info/entry_points.txt
dv_tools-0.1.2.dist-info/RECORD
