Metadata-Version: 2.4
Name: dv-tools
Version: 0.1.2
Summary: Collection of CLI tools for development
Requires-Python: >=3.10.12
Requires-Dist: jinja2>=3.1.0
Requires-Dist: openpyxl>=3.1.0
Requires-Dist: pandas>=2.0.0
Requires-Dist: typer>=0.20.0
